homelab_airflow_dags/__init__.py
homelab_airflow_dags/dags/__init__.py
homelab_airflow_dags/dags/load_dag.py
homelab_airflow_dags/dags/my_dags.py
homelab_airflow_dags/dags/test_dag.yaml
homelab_airflow_dags/dags/test_dag_v2.yaml
homelab_airflow_dags-0.3.3.dist-info/METADATA
homelab_airflow_dags-0.3.3.dist-info/WHEEL
homelab_airflow_dags-0.3.3.dist-info/RECORD
